tvrage3-0.1.1.dist-info/RECORD
tvrage3-0.1.1.dist-info/top_level.txt
tvrage3-0.1.1.dist-info/WHEEL
tvrage3-0.1.1.dist-info/METADATA
tvrage3-0.1.1.dist-info/metadata.json
tvrage3-0.1.1.dist-info/DESCRIPTION.rst
tvrage3/__init__.py
tvrage3/api.py
tvrage3/search.py
