Metadata-Version: 2.0
Name: tvrage3
Version: 0.1.1
Summary: Python3 client for accessing tv show information from www.tvrage.com
Home-page: https://github.com/kalind/tvrage3
Author: Kalle Lindqvist
Author-email: kalle.lindqvist@mykolab.com
License: BSD
Keywords: tvrage,tv,show
Platform: UNKNOWN
Classifier: Development Status :: 4 - Beta
Classifier: Intended Audience :: Developers
Classifier: License :: OSI Approved :: BSD License
Classifier: Programming Language :: Python :: 3
Classifier: Programming Language :: Python :: 3.4
Classifier: Operating System :: OS Independent
Requires-Dist: xmltodict
